pyg_engine/__init__.py
pyg_engine/audio/__init__.py
pyg_engine/audio/audio_manager.py
pyg_engine/audio/sound.py
pyg_engine/components/__init__.py
pyg_engine/components/component.py
pyg_engine/components/script.py
pyg_engine/core/__init__.py
pyg_engine/core/debug_interface.py
pyg_engine/core/engine.py
pyg_engine/core/gameobject.py
pyg_engine/core/runnable.py
pyg_engine/core/serialization.py
pyg_engine/etc/pyg_logo.png
pyg_engine/etc/pyg_logo_transparent.png
pyg_engine/events/__init__.py
pyg_engine/events/event.py
pyg_engine/events/event_manager.py
pyg_engine/input/__init__.py
pyg_engine/input/input.py
pyg_engine/physics/__init__.py
pyg_engine/physics/collider.py
pyg_engine/physics/material.py
pyg_engine/physics/physics_system.py
pyg_engine/physics/rigidbody.py
pyg_engine/physics/sprite_collider.py
pyg_engine/rendering/__init__.py
pyg_engine/rendering/animator.py
pyg_engine/rendering/camera.py
pyg_engine/rendering/sprite.py
pyg_engine/rendering/sprite_sheet.py
pyg_engine/ui/__init__.py
pyg_engine/ui/anchors.py
pyg_engine/ui/canvas.py
pyg_engine/ui/ui_button.py
pyg_engine/ui/ui_canvas.py
pyg_engine/ui/ui_element.py
pyg_engine/ui/ui_label.py
pyg_engine/ui/ui_panel.py
pyg_engine/ui/ui_text_input.py
pyg_engine/utilities/__init__.py
pyg_engine/utilities/built_tools.py
pyg_engine/utilities/cli.py
pyg_engine/utilities/color.py
pyg_engine/utilities/object_types.py
pyg_engine/utilities/sprite_loader.py
pyg_engine/utilities/vector2.py
pyg_engine-1.0.0a6.dist-info/licenses/LICENSE
pyg_engine-1.0.0a6.dist-info/METADATA
pyg_engine-1.0.0a6.dist-info/WHEEL
pyg_engine-1.0.0a6.dist-info/entry_points.txt
pyg_engine-1.0.0a6.dist-info/top_level.txt
pyg_engine-1.0.0a6.dist-info/RECORD
